Workbook

Sheet Cover
B2: HCP TERRITORY ROI CALCULATOR
B3: Pharma Commercial Analytics — Diabetes Portfolio
B4: HCP Targeting & Brand Performance Analytics Project
B6: PURPOSE | C6: Model the commercial impact of HCP targeting decisions
B7: SCOPE | C7: 4 HCP segments · 4 territories · 3 scenarios
B8: DATA SOURCE | C8: CMS Medicare Part D 2022; CMS Open Payments 2022
B10: WORKSHEET GUIDE
B11: 1. Inputs | C11: All configurable assumptions — change these to model scenarios
B12: 2. Segment ROI | C12: Per-segment call cost, Rx lift and ROI calculation
B13: 3. Territory Compare | C13: Side-by-side ROI across 4 territory compositions
B14: 4. Scenario Analysis | C14: Base / Optimistic / Pessimistic sensitivities
B15: 5. Priority Matrix | C15: Which HCPs to target first — value vs effort quadrant
B17: COLOUR KEY
B18: ■ | C18: Blue text — user input (change these)
B19: ■ | C19: Black text — calculated formula (do not edit)
B20: ■ | C20: Green text — cross-sheet link

Sheet Inputs
B2: MODEL INPUTS — CHANGE THESE TO RUN SCENARIOS
B4: A. COST & REVENUE ASSUMPTIONS
B5: Cost per field sales call ($) | C5: 180 | D5: Source: Industry benchmark; Bain & Company 2023
B6: Net revenue per branded Rx fill ($) | C6: 45 | D6: Source: Avg branded diabetes Rx margin estimate
B7: Average fills per HCP per year (base) | C7: 120 | D7: Baseline annual fills before intervention
B8: Rep territory size (HCPs) | C8: 250 | D8: Total HCPs in a standard rep territory
B9: Working weeks per year | C9: 48 | D9: Excludes 4 weeks PTO/training
B10: Calls per rep per day | C10: 6 | D10: Average field calls per rep per day
B12: B. CALL CADENCE (days between visits)
B13: High Value — cadence (days) | C13: 28 | D13: Every 4 weeks — defend Rx share
B14: Growth — cadence (days) | C14: 42 | D14: Every 6 weeks — convert & grow
B15: Maintenance — cadence (days) | C15: 84 | D15: Every 12 weeks — keep warm
B16: Deprioritise — cadence (days) | C16: 180 | D16: Every 6 months — minimal touch
B18: C. EXPECTED Rx LIFT PER CALL (% incremental fills)
B19: High Value — Rx lift per call (%) | C19: 0.08 | D19: Defending existing high-volume prescribers
B20: Growth — Rx lift per call (%) | C20: 0.12 | D20: Converting rising prescribers (highest marginal gain)
B21: Maintenance — Rx lift per call (%) | C21: 0.04 | D21: Low marginal gain; calls preserve not grow
B22: Deprioritise — Rx lift per call (%) | C22: 0.02 | D22: Minimal engagement value
B24: D. TERRITORY HCP MIX (number of HCPs per segment)
B25: High Value HCPs | C25: 30 | D25: Approx 12% of territory — highest-priority accounts
B26: Growth HCPs | C26: 45 | D26: Approx 18% — converting prescribers
B27: Maintenance HCPs | C27: 90 | D27: Approx 36% — established, defending share
B28: Deprioritise HCPs | C28: 85 | D28: Approx 34% — minimal commercial value
B30: Total HCPs (check) | C30: =C25+C26+C27+C28 -> 250 | D30: Should equal territory size input (C8)

Sheet Segment ROI
B2: SEGMENT-LEVEL ROI ANALYSIS — ANNUAL TERRITORY VIEW
B3: All inputs pulled from Inputs sheet. Change assumptions there to update this model.
B5: Segment | C5: HCPs | D5: Calls/Year | E5: Call Cost ($) | F5: Rx Lift (fills) | G5: Revenue Lift ($) | H5: Net ROI ($) | I5: ROI %
B6: High Value | C6: =Inputs!C25 -> 30 | D6: =ROUND(Inputs!C25*(365/Inputs!C13),0) -> 391 | E6: =D6*Inputs!$C$5 -> 70380 | F6: =ROUND(Inputs!C25*Inputs!$C$7*Inputs!C19*(365/Inputs!C13),0) -> 3754 | G6: =F6*Inputs!$C$6 -> 168930 | H6: =G6-E6 -> 98550 | I6: =IFERROR((G6-E6)/E6,0) -> 1.4002558
B7: Growth | C7: =Inputs!C26 -> 45 | D7: =ROUND(Inputs!C26*(365/Inputs!C14),0) -> 391 | E7: =D7*Inputs!$C$5 -> 70380 | F7: =ROUND(Inputs!C26*Inputs!$C$7*Inputs!C20*(365/Inputs!C14),0) -> 5631 | G7: =F7*Inputs!$C$6 -> 253395 | H7: =G7-E7 -> 183015 | I7: =IFERROR((G7-E7)/E7,0) -> 2.6003836
B8: Maintenance | C8: =Inputs!C27 -> 90 | D8: =ROUND(Inputs!C27*(365/Inputs!C15),0) -> 391 | E8: =D8*Inputs!$C$5 -> 70380 | F8: =ROUND(Inputs!C27*Inputs!$C$7*Inputs!C21*(365/Inputs!C15),0) -> 1877 | G8: =F8*Inputs!$C$6 -> 84465 | H8: =G8-E8 -> 14085 | I8: =IFERROR((G8-E8)/E8,0) -> 0.20012788
B9: Deprioritise | C9: =Inputs!C28 -> 85 | D9: =ROUND(Inputs!C28*(365/Inputs!C16),0) -> 172 | E9: =D9*Inputs!$C$5 -> 30960 | F9: =ROUND(Inputs!C28*Inputs!$C$7*Inputs!C22*(365/Inputs!C16),0) -> 414 | G9: =F9*Inputs!$C$6 -> 18630 | H9: =G9-E9 -> -12330 | I9: =IFERROR((G9-E9)/E9,0) -> -0.39825581
B10: TOTAL TERRITORY | C10: =SUM(C6:C9) -> 250 | D10: =SUM(D6:D9) -> 1345 | E10: =SUM(E6:E9) -> 242100 | F10: =SUM(F6:F9) -> 11676 | G10: =SUM(G6:G9) -> 525420 | H10: =SUM(H6:H9) -> 283320 | I10: =IFERROR(SUM(G6:G9)/SUM(E6:E9)-1,0) -> 1.1702602
B12: KEY INSIGHT: Growth segment typically delivers highest ROI per call — rising prescribers have highest marginal Rx lift from each visit.

Sheet Territory Compare
B2: TERRITORY COMPOSITION COMPARISON — 4 TERRITORY TYPES
B5: Metric | C5: Balanced (Base Case) | D5: High Value Heavy | E5: Growth Focused | F5: Maintenance Mode
B6: High Value HCPs | C6: 30 | D6: 70 | E6: 10 | F6: 10
B7: Growth HCPs | C7: 45 | D7: 20 | E7: 90 | F7: 20
B8: Maintenance HCPs | C8: 90 | D8: 60 | E8: 60 | F8: 160
B9: Deprioritise HCPs | C9: 85 | D9: 100 | E9: 90 | F9: 60
B10: Total HCPs | C10: =SUM(C6:C9) -> 250 | D10: =SUM(D6:D9) -> 250 | E10: =SUM(E6:E9) -> 250 | F10: =SUM(F6:F9) -> 250
B11: Total Calls/Year | C11: =ROUND(C6*(365/Inputs!$C$13)+C7*(365/Inputs!$C$14)+C8*(365/Inputs!$C$15)+C9*(365/Inputs!$C$16),0) -> 1346 | D11: =ROUND(D6*(365/Inputs!$C$13)+D7*(365/Inputs!$C$14)+D8*(365/Inputs!$C$15)+D9*(365/Inputs!$C$16),0) -> 1550 | E11: =ROUND(E6*(365/Inputs!$C$13)+E7*(365/Inputs!$C$14)+E8*(365/Inputs!$C$15)+E9*(365/Inputs!$C$16),0) -> 1356 | F11: =ROUND(F6*(365/Inputs!$C$13)+F7*(365/Inputs!$C$14)+F8*(365/Inputs!$C$15)+F9*(365/Inputs!$C$16),0) -> 1121
B12: Total Call Cost ($) | C12: =C11*Inputs!$C$5 -> 242280 | D12: =D11*Inputs!$C$5 -> 279000 | E12: =E11*Inputs!$C$5 -> 244080 | F12: =F11*Inputs!$C$5 -> 201780
B13: Revenue Lift ($) | C13: =ROUND((C6*Inputs!$C$7*Inputs!$C$19*(365/Inputs!$C$13)+C7*Inputs!$C$7*Inputs!$C$20*(365/Inputs!$C$14)+C8*Inputs!$C$7*Inputs!$C$21*(365/Inputs!$C$15)+C9*Inputs!$C$7*Inputs!$C$22*(365/Inputs!$C$16))*Inputs!$C$6,0) -> 525444 | D13: =ROUND((D6*Inputs!$C$7*Inputs!$C$19*(365/Inputs!$C$13)+D7*Inputs!$C$7*Inputs!$C$20*(365/Inputs!$C$14)+D8*Inputs!$C$7*Inputs!$C$21*(365/Inputs!$C$15)+D9*Inputs!$C$7*Inputs!$C$22*(365/Inputs!$C$16))*Inputs!$C$6,0) -> 585043 | E13: =ROUND((E6*Inputs!$C$7*Inputs!$C$19*(365/Inputs!$C$13)+E7*Inputs!$C$7*Inputs!$C$20*(365/Inputs!$C$14)+E8*Inputs!$C$7*Inputs!$C$21*(365/Inputs!$C$15)+E9*Inputs!$C$7*Inputs!$C$22*(365/Inputs!$C$16))*Inputs!$C$6,0) -> 639167 | F13: =ROUND((F6*Inputs!$C$7*Inputs!$C$19*(365/Inputs!$C$13)+F7*Inputs!$C$7*Inputs!$C$20*(365/Inputs!$C$14)+F8*Inputs!$C$7*Inputs!$C$21*(365/Inputs!$C$15)+F9*Inputs!$C$7*Inputs!$C$22*(365/Inputs!$C$16))*Inputs!$C$6,0) -> 332254
B14: Net ROI ($) | C14: =C13-C12 -> 283164 | D14: =D13-D12 -> 306043 | E14: =E13-E12 -> 395087 | F14: =F13-F12 -> 130474
B15: ROI % | C15: =IFERROR(C14/C12,0) -> 1.1687469 | D15: =IFERROR(D14/D12,0) -> 1.0969283 | E15: =IFERROR(E14/E12,0) -> 1.6186783 | F15: =IFERROR(F14/F12,0) -> 0.64661513
B16: ROI per HCP ($) | C16: =IFERROR(C14/C10,0) -> 1132.656 | D16: =IFERROR(D14/D10,0) -> 1224.172 | E16: =IFERROR(E14/E10,0) -> 1580.348 | F16: =IFERROR(F14/F10,0) -> 521.896

Sheet Scenario Analysis
B2: SCENARIO ANALYSIS — BASE / OPTIMISTIC / PESSIMISTIC
B5: Assumption | C5: Base Case | D5: Optimistic | E5: Pessimistic
B6: Call adherence rate (%) | C6: =Inputs!$C$9*Inputs!$C$10*5/Inputs!$C$8 -> 5.76 | D6: 1.15 | E6: 0.7
B7: Rx lift multiplier | C7: 1 | D7: 1.3 | E7: 0.7
B8: Cost per call ($) | C8: =Inputs!$C$5 -> 180 | D8: 0.9 | E8: 1.15
B9: HCP segment mix — HV % | C9: =Inputs!$C$25/Inputs!$C$8 -> 0.12 | D9: 0.18 | E9: 0.08
B11: SCENARIO OUTPUTS
B12: Annual call cost ($) | C12: =Inputs!$C$5*ROUND(Inputs!$C$25*(365/Inputs!$C$13)+Inputs!$C$26*(365/Inputs!$C$14)+Inputs!$C$27*(365/Inputs!$C$15)+Inputs!$C$28*(365/Inputs!$C$16),0) -> 242280 | D12: =C12*0.9 -> 218052 | E12: =C12*1.15 -> 278622
B13: Revenue lift ($) | C13: ='Segment ROI'!G10 -> 525420 | D13: =C13*1.3 -> 683046 | E13: =C13*0.7 -> 367794
B14: Net ROI ($) | C14: =C12-C11 -> 242280 | D14: =D13-D12 -> 464994 | E14: =E13-E12 -> 89172
B15: ROI % | C15: =IFERROR(C12/C11,0) -> 0 | D15: =IFERROR(D12/D11,0) -> 0 | E15: =IFERROR(E12/E11,0) -> 0
B16: Incremental Rx fills | C16: ='Segment ROI'!F10 -> 11676 | D16: =C16*1.3 -> 15178.8 | E16: =C16*0.7 -> 8173.2

Sheet Priority Matrix
B2: HCP PRIORITY MATRIX — VALUE vs CALL EFFORT
B5: Segment | C5: HCPs | D5: Annual Calls per HCP | E5: Call Cost per HCP ($) | F5: Rev Lift per HCP ($) | G5: Net ROI per HCP ($) | H5: Prioritisation Decision
B6: High Value | C6: =Inputs!C25 -> 30 | D6: =ROUND(365/Inputs!C13,1) -> 13 | E6: =ROUND((365/Inputs!C13)*Inputs!$C$5,0) -> 2346 | F6: =ROUND(Inputs!$C$7*Inputs!C19*(365/Inputs!C13)*Inputs!$C$6,0) -> 5631 | G6: =F6-E6 -> 3285 | H6: INVEST FIRST — Highest volume, defend at all costs. Personal relationship priority.
B7: Growth | C7: =Inputs!C26 -> 45 | D7: =ROUND(365/Inputs!C14,1) -> 8.7 | E7: =ROUND((365/Inputs!C14)*Inputs!$C$5,0) -> 1564 | F7: =ROUND(Inputs!$C$7*Inputs!C20*(365/Inputs!C14)*Inputs!$C$6,0) -> 5631 | G7: =F7-E7 -> 4067 | H7: PRIORITISE — Highest ROI per call. Converting prescribers = compounding future value.
B8: Maintenance | C8: =Inputs!C27 -> 90 | D8: =ROUND(365/Inputs!C15,1) -> 4.3 | E8: =ROUND((365/Inputs!C15)*Inputs!$C$5,0) -> 782 | F8: =ROUND(Inputs!$C$7*Inputs!C21*(365/Inputs!C15)*Inputs!$C$6,0) -> 939 | G8: =F8-E8 -> 157 | H8: MAINTAIN — Sufficient cadence to preserve existing share. Don't over-invest.
B9: Deprioritise | C9: =Inputs!C28 -> 85 | D9: =ROUND(365/Inputs!C16,1) -> 2 | E9: =ROUND((365/Inputs!C16)*Inputs!$C$5,0) -> 365 | F9: =ROUND(Inputs!$C$7*Inputs!C22*(365/Inputs!C16)*Inputs!$C$6,0) -> 219 | G9: =F9-E9 -> -146 | H9: MINIMAL TOUCH — Digital channels only. Redirect rep time to Growth & HV segments.
B11: Source: Call cost = Inputs!C5 ($180/call industry benchmark). Rx lift rates based on pharma CRM closed-loop measurement benchmarks.
